ipaparser/__init__.py
ipaparser/definitions.py
ipaparser/exceptions.py
ipaparser/features.py
ipaparser/_code/__init__.py
ipaparser/_code/cacher.py
ipaparser/_code/combiner.py
ipaparser/_code/data.py
ipaparser/_code/data_types.py
ipaparser/_code/feature_helper.py
ipaparser/_code/ipa.py
ipaparser/_code/ipa_config.py
ipaparser/_code/ipa_symbol.py
ipaparser/_code/matcher.py
ipaparser/_code/parser.py
ipaparser/_code/phonetics.py
ipaparser/_code/raw_symbol.py
ipaparser/_code/strings.py
ipaparser/_code/definitions/__init__.py
ipaparser/_code/definitions/brackets.py
ipaparser/_code/definitions/transcription.py
ipaparser/_code/exceptions/__init__.py
ipaparser/_code/exceptions/bracket_strategy.py
ipaparser/_code/exceptions/combined_length.py
ipaparser/_code/exceptions/combined_sound.py
ipaparser/_code/exceptions/enclosing.py
ipaparser/_code/exceptions/feature.py
ipaparser/_code/exceptions/feature_kind.py
ipaparser/_code/exceptions/incompatible_types.py
ipaparser/_code/features/__init__.py
ipaparser/_code/features/airflow.py
ipaparser/_code/features/articulation.py
ipaparser/_code/features/aspiration.py
ipaparser/_code/features/backness.py
ipaparser/_code/features/breaks.py
ipaparser/_code/features/feature.py
ipaparser/_code/features/height.py
ipaparser/_code/features/intonation.py
ipaparser/_code/features/length.py
ipaparser/_code/features/manner.py
ipaparser/_code/features/place.py
ipaparser/_code/features/release.py
ipaparser/_code/features/roundedness.py
ipaparser/_code/features/secondary.py
ipaparser/_code/features/sound.py
ipaparser/_code/features/strength.py
ipaparser/_code/features/stress.py
ipaparser/_code/features/suprasegmental.py
ipaparser/_code/features/syllabicity.py
ipaparser/_code/features/symbol.py
ipaparser/_code/features/tone.py
ipaparser/_code/features/voice.py
ipaparser/_data/brackets
ipaparser/_data/breaks
ipaparser/_data/combining-basic
ipaparser/_data/combining-main
ipaparser/_data/combining-meta
ipaparser/_data/substitutions
ipaparser-1.0.0.dist-info/LICENSE
ipaparser-1.0.0.dist-info/METADATA
ipaparser-1.0.0.dist-info/WHEEL
ipaparser-1.0.0.dist-info/top_level.txt
ipaparser-1.0.0.dist-info/RECORD
