Metadata-Version: 2.1
Name: ipaparser
Version: 1.0.0
Summary: Phonetically aware library for parsing IPA transcriptions
Home-page: https://github.com/danmysak/ipa-parser
Author: Danylo Mysak
Author-email: danmysak@gmail.com
License: UNKNOWN
Project-URL: Bug Tracker, https://github.com/danmysak/ipa-parser/issues
Platform: UNKNOWN
Classifier: Programming Language :: Python :: 3
Classifier: License :: OSI Approved :: MIT License
Classifier: Operating System :: OS Independent
Requires-Python: >=3.9
License-File: LICENSE
